README.md
setup.py
mqttmpd/__init__.py
mqttmpd/controller.py
mqttmpd.egg-info/PKG-INFO
mqttmpd.egg-info/SOURCES.txt
mqttmpd.egg-info/dependency_links.txt
mqttmpd.egg-info/not-zip-safe
mqttmpd.egg-info/requires.txt
mqttmpd.egg-info/top_level.txt