Metadata-Version: 1.1
Name: mqttmpd
Version: 1.0.0
Summary: MQTT to MPD bridge using python
Home-page: https://github.com/haum/mqtt_mpd
Author: Mathieu Gaborit, HAUM
Author-email: mathieu@haum.org
License: beer-ware
Platform: UNKNOWN
Classifier: Programming Language :: Python :: 3
Classifier: Operating System :: OS Independent
